insightpkg/__init__.py
insightpkg/cli.py
insightpkg-0.1.3.dist-info/licenses/LICENSE
insightpkg-0.1.3.dist-info/METADATA
insightpkg-0.1.3.dist-info/WHEEL
insightpkg-0.1.3.dist-info/entry_points.txt
insightpkg-0.1.3.dist-info/top_level.txt
insightpkg-0.1.3.dist-info/RECORD
