Metadata-Version: 2.4
Name: insightpkg
Version: 0.1.3
Summary: A simple CLI tool to fetch metadata from PyPI
Author-email: Mayank <mayankchoudharysept17@gmail.com>
License-Expression: MIT
Requires-Python: >=3.7
License-File: LICENSE
Requires-Dist: requests
Dynamic: license-file
